eslearn/__init__.py
eslearn/base.py
eslearn/model_evaluator.py
eslearn/setup.py
eslearn/GUI/__init__.py
eslearn/GUI/easylearn_data_loading_gui.py
eslearn/GUI/easylearn_data_loading_run.py
eslearn/GUI/easylearn_feature_engineering.py
eslearn/GUI/easylearn_feature_engineering_gui.py
eslearn/GUI/easylearn_feature_engineering_run.py
eslearn/GUI/easylearn_machine_learning_gui.py
eslearn/GUI/easylearn_machine_learning_run.py
eslearn/GUI/easylearn_main_gui.py
eslearn/GUI/easylearn_main_run.py
eslearn/GUI/easylearn_model_evaluation_gui.py
eslearn/GUI/easylearn_model_evaluation_run.py
eslearn/GUI/lc_ui2py_for_data_loading.py
eslearn/GUI/lc_ui2py_for_feature_engineering.py
eslearn/GUI/lc_ui2py_for_machine_learning.py
eslearn/GUI/lc_ui2py_for_main.py
eslearn/GUI/lc_ui2py_for_model_evaluation.py
eslearn/GUI/start_.py
eslearn/GUI/start_test.py
eslearn/GUI/test_pipeline.py
eslearn/IO/__init__.py
eslearn/IO/el_niiProcessor.py
eslearn/IO/write2nii.py
eslearn/examples/__init__.py
eslearn/examples/demo_pca_relieff_svc.py
eslearn/examples/demo_pca_rfecv_svc.py
eslearn/img/GUI_data_loading.png
eslearn/img/GUI_main.png
eslearn/img/__init__.py
eslearn/img/classification_performances.png
eslearn/img/dec_label.png
eslearn/img/dimreduction.png
eslearn/img/e1288c865f13daac2eb25d3f8acc574.png
eslearn/img/easylearn-flow-chart.jpg
eslearn/img/feature_selection.png
eslearn/img/machine_learning.png
eslearn/img/perf.png
eslearn/img/preprocessing.png
eslearn/img/unbalance_treatment.png
eslearn/img/wei.jpg
eslearn/logo/__init__.py
eslearn/logo/close.png
eslearn/logo/logo-dms.png
eslearn/logo/logo-lower.jpg
eslearn/logo/logo-upper.ico
eslearn/logo/logo-upper.jpg
eslearn/logo/logo_v1.png
eslearn/logo/run.png
eslearn/machine_learning/__init__.py
eslearn/machine_learning/classfication/__init__.py
eslearn/machine_learning/classfication/_base_classificaition.py
eslearn/machine_learning/classfication/classificaition.py
eslearn/machine_learning/classfication/lc_pipeline_test.py
easylearn-0.1.20a0.dist-info/LICENSE
easylearn-0.1.20a0.dist-info/METADATA
easylearn-0.1.20a0.dist-info/WHEEL
easylearn-0.1.20a0.dist-info/top_level.txt
easylearn-0.1.20a0.dist-info/RECORD
