Metadata-Version: 2.1
Name: easylearn
Version: 0.1.20a0
Summary: This project is designed for machine learning in resting-state fMRI field
Home-page: https://github.com/easylearn-fmri/
Author: Chao Li; Mengshi Dong
Author-email: lichao19870617@gmail.com
Maintainer: Chao Li; Mengshi Dong
Maintainer-email: lichao19870617@gmail.com
License: MIT License
Platform: all
Classifier: Development Status :: 2 - Pre-Alpha
Classifier: License :: OSI Approved :: MIT License
Classifier: Intended Audience :: Science/Research
Classifier: Intended Audience :: Education
Classifier: Natural Language :: English
Classifier: Natural Language :: Chinese (Simplified)
Classifier: Programming Language :: Python :: 3
Classifier: Operating System :: OS Independent
Requires-Python: >=3.5
